Metadata-Version: 1.1
Name: build-proj
Version: 0.0.1
Summary: An alterative to make
Home-page: http://github.com/Ehnryu/build
Author: Ehnryu/Sakurai07
Author-email: blzzardst0rm@gmail.com
License: MIT
Keywords: build,make
Platform: UNKNOWN
Classifier: Programming Language :: Python :: 3
